isiterable.cpython-310.so
isiterable-1.0.post1.dist-info/LICENSE
isiterable-1.0.post1.dist-info/METADATA
isiterable-1.0.post1.dist-info/WHEEL
isiterable-1.0.post1.dist-info/top_level.txt
isiterable-1.0.post1.dist-info/RECORD
