Metadata-Version: 2.1
Name: isiterable
Version: 1.0.post1
Summary: Module that provides the isiterable function to check if an object is iterable quickly for code in production.
Home-page: https://github.com/CosmicLivest/isiterable
Author: CosmicLivest
Author-email: ezequielfx15@gmail.com
License: Unlicense License
Project-URL: Source, https://github.com/CosmicLivest/isiterable
Project-URL: Tracker, https://github.com/CosmicLivest/isiterable/issues
Platform: UNKNOWN
Classifier: Development Status :: 4 - Beta
Classifier: Intended Audience :: Developers
Classifier: Topic :: Utilities
Classifier: License :: OSI Approved :: The Unlicense (Unlicense)
Classifier: Programming Language :: C
Classifier: Programming Language :: Python :: 2
Classifier: Programming Language :: Python :: 2.7
Classifier: Programming Language :: Python :: 3
Classifier: Programming Language :: Python :: 3.6
Classifier: Programming Language :: Python :: 3.7
Classifier: Programming Language :: Python :: 3.8
Classifier: Programming Language :: Python :: 3.9
Classifier: Programming Language :: Python :: 3.10
License-File: LICENSE
